ffmpeg_progress/__init__.py
ffmpeg_progress/__main__.py
ffmpeg_progress/constants.py
ffmpeg_progress/exceptions.py
ffmpeg_progress/lib.py
ffmpeg_progress/main.py
ffmpeg_progress/py.typed
ffmpeg_progress/typing.py
ffmpeg_progress/utils.py
ffmpeg_progress-0.0.6.dist-info/METADATA
ffmpeg_progress-0.0.6.dist-info/WHEEL
ffmpeg_progress-0.0.6.dist-info/entry_points.txt
ffmpeg_progress-0.0.6.dist-info/licenses/LICENSE.txt
ffmpeg_progress-0.0.6.dist-info/RECORD
