Metadata-Version: 2.4
Name: ffmpeg-progress
Version: 0.0.6
Summary: Get progress information for an ffmpeg process.
License-Expression: MIT
License-File: LICENSE.txt
Keywords: command line,ffmpeg
Author: Andrew Udvare
Author-email: audvare@gmail.com
Requires-Python: >=3.10,<4.0
Classifier: Development Status :: 4 - Beta
Classifier: Intended Audience :: Developers
Classifier: Programming Language :: Python
Classifier: Programming Language :: Python :: 3.10
Classifier: Programming Language :: Python :: 3.11
Classifier: Programming Language :: Python :: 3.12
Classifier: Programming Language :: Python :: 3.13
Classifier: Programming Language :: Python :: 3.14
Classifier: Typing :: Typed
Classifier: Topic :: Multimedia :: Sound/Audio
Classifier: Topic :: Multimedia :: Sound/Audio :: Conversion
Classifier: Topic :: Multimedia :: Video
Classifier: Topic :: Multimedia :: Video :: Conversion
Requires-Dist: bascom (>=0.0.4,<0.0.5)
Requires-Dist: click (>=8.3.0,<9.0.0)
Requires-Dist: psutil (>=7.1.3,<8.0.0)
Requires-Dist: typing-extensions (>=4.15.0,<5.0.0)
Project-URL: Documentation, https://ffmpeg-progress.readthedocs.org
Project-URL: Homepage, https://tatsh.github.io/ffmpeg-progress/
Project-URL: Issues, https://github.com/Tatsh/ffmpeg-progress/issues
Project-URL: Repository, https://github.com/Tatsh/ffmpeg-progress
